demo_poetry_davor_a/__init__.py
demo_poetry_davor_a-0.1.2.dist-info/entry_points.txt
demo_poetry_davor_a-0.1.2.dist-info/WHEEL
demo_poetry_davor_a-0.1.2.dist-info/METADATA
demo_poetry_davor_a-0.1.2.dist-info/RECORD
