Metadata-Version: 2.1
Name: demo-poetry-davor-a
Version: 0.1.2
Summary: 
Author: Jorge
Author-email: larajorge11@gmail.com
Requires-Python: >=3.9,<4.0
Classifier: Programming Language :: Python :: 3
Classifier: Programming Language :: Python :: 3.9
Requires-Dist: loguru
Requires-Dist: psutil
